1、栈内存的解析

对于栈的解析，这里现在对以下代码的运行过程进行解析：

```java
package com.rzcoding;

public class Client {
    public static void main(String[] args) {
        Client client = new Client();
        System.out.println(client.getValue());
    }

    public int getValue() {
        int a = 1;
        int b = 2;
        int c = (a+b)*10;
        return c;
    }
}

```

通过javap -c Client.class命令对上述编译的代码进行解析：

```java
Compiled from "Client.java"
public class com.rzcoding.Client {
  public com.rzcoding.Client();
    Code:
       0: aload_0
       1: invokespecial #1                  // Method java/lang/Object."<init>":()V
       4: return

  public static void main(java.lang.String[]);
    Code:
       0: new           #2                  // class com/rzcoding/Client
       3: dup
       4: invokespecial #3                  // Method "<init>":()V
       7: astore_1
       8: getstatic     #4                  // Field java/lang/System.out:Ljava/io/PrintStream;
      11: aload_1
      12: invokevirtual #5                  // Method getValue:()I
      15: invokevirtual #6                  // Method java/io/PrintStream.println:(I)V
      18: return

  public int getValue();
    Code:
       0: iconst_1 // 将int类型1压入栈顶
       1: istore_1 // 将栈顶的数存入到局部变量1中 a
       2: iconst_2 // 将int类型2压入栈顶
       3: istore_2 // 将栈顶的数存入到局部变量2中 b
       4: iload_1  // 将第1个int型a本地变量推送至栈顶 
       5: iload_2  // 将第2个int型b本地变量推送至栈顶 
       6: iadd     // 将栈中的数据弹出，执行相加操作，同时压入栈顶
       7: bipush        10 //  将单字节的常量值(-128~127)推送至栈顶
       9: imul     // 执行相乘操作，同时将结果压入栈顶
      10: istore_3 // 将栈顶的数存入到局部变量3中 c
      11: iload_3  // 将第3个int型c本地变量推送至栈顶 
      12: ireturn  // 从当前方法返回int 将栈顶数值返回
}
```



可以当作gc-root的对象： 线程本地变量，静态变量



2、java内存模型

java线程模型：是指java线程有自己私有的工作内存。修改共享变量的时候，会先复制一份到工作内存中，然后才能操作。

原子操作：

```java
lock（锁定）：作用于主内存的变量，把一个变量标识为一条线程独占状态。
unlock（解锁）：作用于主内存变量，把一个处于锁定状态的变量释放出来，释放后的变量才可以被其他线程锁定。
read（读取）：作用于主内存变量，把一个变量值从主内存传输到线程的工作内存中，以便随后的load动作使用
load（载入）：作用于工作内存的变量，它把read操作从主内存中得到的变量值放入工作内存的变量副本中。
use（使用）：作用于工作内存的变量，把工作内存中的一个变量值传递给执行引擎，每当虚拟机遇到一个需要使用变量的值的字节码指令时将会执行这个操作。
assign（赋值）：作用于工作内存的变量，它把一个从执行引擎接收到的值赋值给工作内存的变量，每当虚拟机遇到一个给变量赋值的字节码指令时执行这个操作。
store（存储）：作用于工作内存的变量，把工作内存中的一个变量的值传送到主内存中，以便随后的write的操作。
write（写入）：作用于主内存的变量，它把store操作从工作内存中一个变量的值传送到主内存的变量中。
```



总线嗅探：线程对总线进行监听，当监听到store的操作后，会让工作内存的值失效掉。



volatile:  会在汇编语句前面加 lock：就是说执行了assign指令后，会马上执行 store和writer操作，同时store和write操作时加锁的。



3、aqs抽象队列同步器

两个属性： state 和 thread 

自旋 cas locksurport



4、hashmap

java7   数组 + 链表      为什么初始容量时2的指数次幂，因为要保证  h & [lent -1 ] 和 h%lent的指相等，所以要为2的指数次幂。为什么要用位运算：因为比较快，同时出现hash碰撞的时候，插入到链表中的方法是头插法。

线程不安全，数据会丢失，会产生死锁

扩容因子为什么是0.75



java8： 链表转红黑树的值： 当链表的长度到达8的时候，会去查看数组的长度是否小于64，如果是的话，优先扩容，否则就转红黑树



5、spring源码

BeanFactory用于存储bean